otel_file_exporter/__init__.py
otel_file_exporter/otel.py
otel_file_exporter-0.1.1.dist-info/METADATA
otel_file_exporter-0.1.1.dist-info/WHEEL
otel_file_exporter-0.1.1.dist-info/top_level.txt
otel_file_exporter-0.1.1.dist-info/RECORD
