Metadata-Version: 2.4
Name: otel_file_exporter
Version: 0.1.1
Summary: Lightweight OpenTelemetry file exporter that writes traces, logs and metrics to local JSON Lines files
Project-URL: Homepage, https://github.com/Brishen/otel_file_exporter
Project-URL: Source, https://github.com/Brishen/otel_file_exporter
Project-URL: Issues, https://github.com/Brishen/otel_file_exporter/issues
Project-URL: Changelog, https://github.com/Brishen/otel_file_exporter/releases
Keywords: opentelemetry,tracing,logging,metrics,jsonl,observability
Classifier: Development Status :: 4 - Beta
Classifier: License :: OSI Approved :: MIT License
Classifier: Programming Language :: Python :: 3
Classifier: Programming Language :: Python :: 3 :: Only
Classifier: Programming Language :: Python :: 3.13
Classifier: Intended Audience :: Developers
Classifier: Operating System :: OS Independent
Classifier: Framework :: FastAPI
Classifier: Topic :: Software Development :: Libraries :: Python Modules
Classifier: Topic :: System :: Logging
Classifier: Topic :: System :: Monitoring
Requires-Python: >=3.13
Requires-Dist: opentelemetry-api>=1.36.0
Requires-Dist: opentelemetry-exporter-otlp>=1.36.0
Requires-Dist: opentelemetry-instrumentation-fastapi>=0.57b0
Requires-Dist: opentelemetry-instrumentation-logging>=0.57b0
Requires-Dist: opentelemetry-propagator-b3>=1.36.0
Requires-Dist: opentelemetry-sdk>=1.36.0
Requires-Dist: sqlalchemy>=2.0
Provides-Extra: web
Requires-Dist: fastapi>=0.116.1; extra == "web"
Requires-Dist: uvicorn>=0.35.0; extra == "web"
